refrot/__init__.py
refrot/__main__.py
refrot/hparser.py
refrot/spider.py
refrot-1.4.3.dist-info/licenses/LICENSE
refrot-1.4.3.dist-info/METADATA
refrot-1.4.3.dist-info/WHEEL
refrot-1.4.3.dist-info/entry_points.txt
refrot-1.4.3.dist-info/top_level.txt
refrot-1.4.3.dist-info/RECORD
