Metadata-Version: 2.4
Name: refrot
Version: 1.4.3
Summary: Verify website links
Author-email: Craig Howard <craig@seagrape.us>
Project-URL: Homepage, https://seagrape.us/refrot.html
Project-URL: Repository, https://pypi.org/project/refrot/
Project-URL: Changelog, https://seagrape.us/refrot-history.html
Classifier: Programming Language :: Python :: 3
Classifier: License :: OSI Approved :: MIT License
Classifier: Operating System :: OS Independent
License-File: LICENSE
Requires-Dist: requests
Dynamic: license-file
